README.md
setup.cfg
setup.py
gaussian_space/Basedistribution.py
gaussian_space/Binomial.py
gaussian_space/Gauss.py
gaussian_space/__init__.py
gaussian_space.egg-info/PKG-INFO
gaussian_space.egg-info/SOURCES.txt
gaussian_space.egg-info/dependency_links.txt
gaussian_space.egg-info/not-zip-safe
gaussian_space.egg-info/top_level.txt