Metadata-Version: 1.0
Name: gaussian-space
Version: 1.0
Summary: Statistics
Home-page: UNKNOWN
Author: Sashwata Banerjee
Author-email: sashwata21@gmail.com
License: UNKNOWN
Platform: UNKNOWN
